uwsgi_metrics/reservoir.py
uwsgi_metrics/__init__.py
uwsgi_metrics/meter.py
uwsgi_metrics/snapshot.py
uwsgi_metrics/metrics.py
uwsgi_metrics/ewma.py
uwsgi_metrics/timer.py
uwsgi_metrics/counter.py
uwsgi_metrics/__about__.py
uwsgi_metrics/histogram.py
uwsgi_metrics3-1.1.5.dist-info/METADATA
uwsgi_metrics3-1.1.5.dist-info/top_level.txt
uwsgi_metrics3-1.1.5.dist-info/WHEEL
uwsgi_metrics3-1.1.5.dist-info/RECORD
uwsgi_metrics3-1.1.5.dist-info/DESCRIPTION.rst
uwsgi_metrics3-1.1.5.dist-info/metadata.json
